LICENSE
README.md
setup.cfg
setup.py
animediffusion/__init__.py
animediffusion.egg-info/PKG-INFO
animediffusion.egg-info/SOURCES.txt
animediffusion.egg-info/dependency_links.txt
animediffusion.egg-info/requires.txt
animediffusion.egg-info/top_level.txt
animediffusion/pipelines/__init__.py
animediffusion/pipelines/lcm_sd15.py
animediffusion/pipelines/lcm_sdxl.py
animediffusion/utils/__init__.py
animediffusion/utils/data_utils.py
animediffusion/utils/scheduler_list.py