Metadata-Version: 2.1
Name: animediffusion
Version: 0.0.1
Summary: AnimeDiffusion: Anime Image Upscaler
Home-page: https://github.com/kadirnar/AnimeDiffusion
Author: kadirnar
Author-email: kadir.nar@hotmail.com
License: Apache License 2.0
Requires-Python: >=3.8
License-File: LICENSE
